libs/MicroIA_Release_x64.dll
libs/MicroJPEG_Release_x64.dll
libs/MicroTA_Release_x64.dll
libs/__init__.py
libs/libdirp.dll
libs/libexif.dll
libs/libiconv-2.dll
libs/libintl-8.dll
libs/libv_dirp.dll
libs/libv_girp.dll
libs/libv_hirp.dll
libs/libv_iirp.dll
libs/libv_list.ini
libs/thermal.dll
pytsdk/__init__.py
pytsdk/pytsdk.py
pytsdk/libs/MicroIA_Release_x64.dll
pytsdk/libs/MicroJPEG_Release_x64.dll
pytsdk/libs/MicroTA_Release_x64.dll
pytsdk/libs/__init__.py
pytsdk/libs/libdirp.dll
pytsdk/libs/libexif.dll
pytsdk/libs/libiconv-2.dll
pytsdk/libs/libintl-8.dll
pytsdk/libs/libv_dirp.dll
pytsdk/libs/libv_girp.dll
pytsdk/libs/libv_hirp.dll
pytsdk/libs/libv_iirp.dll
pytsdk/libs/libv_list.ini
pytsdk/libs/thermal.dll
pytsdk-0.0.8.dist-info/LICENSE
pytsdk-0.0.8.dist-info/METADATA
pytsdk-0.0.8.dist-info/WHEEL
pytsdk-0.0.8.dist-info/top_level.txt
pytsdk-0.0.8.dist-info/RECORD
