Metadata-Version: 2.1
Name: pytsdk
Version: 0.0.8
Summary: Python version of dji_thermal_sdk
Home-page: https://www.baidu.com
Author: nobody
Author-email: 404937333@qq.com
License: MIT License
Keywords: thermal,dji,tsdk
Platform: Windows
Classifier: Development Status :: 4 - Beta
Classifier: Intended Audience :: Developers
Classifier: License :: OSI Approved :: MIT License
Classifier: Operating System :: Microsoft :: Windows
Classifier: Natural Language :: Chinese (Simplified)
Classifier: Programming Language :: Python :: 3
Classifier: Topic :: Software Development :: Libraries :: Python Modules
License-File: LICENSE
Requires-Dist: numpy
Requires-Dist: enum34 ; python_version < "3.4"
